[
  {
    "title": "Learn high quality tech courses in free of fast at YouTube #blockchaintechnology #rust #tamil",
    "description": "",
    "channelId": "UCJI3CThQtWbDLohsiMs1ryA",
    "channelTitle": "Dall view",
    "videoId": "IKKdmXMl05g",
    "thumbnails": {
      "default": {
        "url": "https://i.ytimg.com/vi/IKKdmXMl05g/default.jpg",
        "width": 120,
        "height": 90
      },
      "medium": {
        "url": "https://i.ytimg.com/vi/IKKdmXMl05g/mqdefault.jpg",
        "width": 320,
        "height": 180
      },
      "high": {
        "url": "https://i.ytimg.com/vi/IKKdmXMl05g/hqdefault.jpg",
        "width": 480,
        "height": 360
      }
    },
    "publishedAt": "2023-12-29T00:49:25Z"
  },
  {
    "title": "Learn programming free of cost #vip #programming #blockchaintechnology #rust #tamil #hindi",
    "description": "",
    "channelId": "UCJI3CThQtWbDLohsiMs1ryA",
    "channelTitle": "Dall view",
    "videoId": "zhM1quozygU",
    "thumbnails": {
      "default": {
        "url": "https://i.ytimg.com/vi/zhM1quozygU/default.jpg",
        "width": 120,
        "height": 90
      },
      "medium": {
        "url": "https://i.ytimg.com/vi/zhM1quozygU/mqdefault.jpg",
        "width": 320,
        "height": 180
      },
      "high": {
        "url": "https://i.ytimg.com/vi/zhM1quozygU/hqdefault.jpg",
        "width": 480,
        "height": 360
      }
    },
    "publishedAt": "2023-12-22T06:44:59Z"
  },
  {
    "title": "What is think native Why should you subscribe @ThinkNative #techinnovation #tamil #rust",
    "description": "",
    "channelId": "UCJI3CThQtWbDLohsiMs1ryA",
    "channelTitle": "Dall view",
    "videoId": "TC8ho6Rq3Gc",
    "thumbnails": {
      "default": {
        "url": "https://i.ytimg.com/vi/TC8ho6Rq3Gc/default.jpg",
        "width": 120,
        "height": 90
      },
      "medium": {
        "url": "https://i.ytimg.com/vi/TC8ho6Rq3Gc/mqdefault.jpg",
        "width": 320,
        "height": 180
      },
      "high": {
        "url": "https://i.ytimg.com/vi/TC8ho6Rq3Gc/hqdefault.jpg",
        "width": 480,
        "height": 360
      }
    },
    "publishedAt": "2023-12-20T16:30:42Z"
  },
  {
    "title": "STORY OF THE GREATEST CRYPTO KINGPIN - RISE AND FALL OF CHANGPENG ZAO - TAMIL",
    "description": "Hello, digital enthusiasts! Welcome to the second episode of our 'Dall View Tech Tales' series. Today, we're diving into the life of ...",
    "channelId": "UCJI3CThQtWbDLohsiMs1ryA",
    "channelTitle": "Dall view",
    "videoId": "OWGZz8fHMUA",
    "thumbnails": {
      "default": {
        "url": "https://i.ytimg.com/vi/OWGZz8fHMUA/default.jpg",
        "width": 120,
        "height": 90
      },
      "medium": {
        "url": "https://i.ytimg.com/vi/OWGZz8fHMUA/mqdefault.jpg",
        "width": 320,
        "height": 180
      },
      "high": {
        "url": "https://i.ytimg.com/vi/OWGZz8fHMUA/hqdefault.jpg",
        "width": 480,
        "height": 360
      }
    },
    "publishedAt": "2023-11-30T06:40:16Z"
  },
  {
    "title": "Dall View Podcast - Tech Kadhaigal #1 - Open AI Sambavam",
    "description": "Welcome to the premiere episode of \"Dall View Podcast - Tech Kadhaigal,\" featuring the riveting story of Sam Altman's journey at ...",
    "channelId": "UCJI3CThQtWbDLohsiMs1ryA",
    "channelTitle": "Dall view",
    "videoId": "_wrgmpG4ovQ",
    "thumbnails": {
      "default": {
        "url": "https://i.ytimg.com/vi/_wrgmpG4ovQ/default.jpg",
        "width": 120,
        "height": 90
      },
      "medium": {
        "url": "https://i.ytimg.com/vi/_wrgmpG4ovQ/mqdefault.jpg",
        "width": 320,
        "height": 180
      },
      "high": {
        "url": "https://i.ytimg.com/vi/_wrgmpG4ovQ/hqdefault.jpg",
        "width": 480,
        "height": 360
      }
    },
    "publishedAt": "2023-11-29T06:45:06Z"
  }
]